AzuriteSDK/Logger.py
AzuriteSDK/__init__.py
AzuriteSDK/config.py
AzuriteSDK/path_manager.py
AzuriteSDK/utils.py
AzuriteSDK/api/app.py
AzuriteSDK/api/plugin.py
azuritesdk-1.0.2.dist-info/METADATA
azuritesdk-1.0.2.dist-info/WHEEL
azuritesdk-1.0.2.dist-info/top_level.txt
azuritesdk-1.0.2.dist-info/RECORD
