Metadata-Version: 2.4
Name: AzuriteSDK
Version: 1.0.2
Summary: SDK for Azurite Modular Discord Framework
Author: kenftr
Author-email: kenftr <contact@kenftr.dev>
License: MIT
Project-URL: Homepage, https://github.com/notkenftr/Azurite
Project-URL: Source, https://github.com/notkenftr/Azurite
Project-URL: Issues, https://github.com/notkenftr/Azurite/issues
Requires-Python: >=3.8
Requires-Dist: discord.py>=2.6.4
Requires-Dist: pyyaml>=6.0.3
Dynamic: author
Dynamic: requires-python
